pg_extended/Types.py
pg_extended/__init__.py
pg_extended/Core/__init__.py
pg_extended/Core/Base/AnimatedValue.py
pg_extended/Core/Base/Callback.py
pg_extended/Core/Base/DynamicValue.py
pg_extended/Core/Base/__init__.py
pg_extended/Core/Composites/CircleArea.py
pg_extended/Core/Composites/RectArea.py
pg_extended/Core/Composites/__init__.py
pg_extended/Game/Scene.py
pg_extended/Game/ViewPort.py
pg_extended/Game/__init__.py
pg_extended/Game/Elements/Entity.py
pg_extended/Game/Elements/Level.py
pg_extended/Game/Elements/Player.py
pg_extended/Game/Elements/SpriteAnimation.py
pg_extended/Game/Elements/TextureAtlas.py
pg_extended/Game/Elements/__init__.py
pg_extended/UI/CopyElement.py
pg_extended/UI/System.py
pg_extended/UI/__init__.py
pg_extended/UI/Compounds/List.py
pg_extended/UI/Compounds/__init__.py
pg_extended/UI/Elements/Button.py
pg_extended/UI/Elements/Circle.py
pg_extended/UI/Elements/Section.py
pg_extended/UI/Elements/Slider.py
pg_extended/UI/Elements/TextBox.py
pg_extended/UI/Elements/TextInput.py
pg_extended/UI/Elements/Toggle.py
pg_extended/UI/Elements/__init__.py
pg_extended/Util/ImgManipulation.py
pg_extended/Util/Misc.py
pg_extended/Util/__init__.py
pg_extended/Window/Core.py
pg_extended/Window/EventManager.py
pg_extended/Window/Lifecycle.py
pg_extended/Window/MainLoop.py
pg_extended/Window/SceneManager.py
pg_extended/Window/SystemManager.py
pg_extended/Window/Utility.py
pg_extended/Window/__init__.py
pg_extended-0.0.1b1.dist-info/licenses/LICENSE
pg_extended-0.0.1b1.dist-info/METADATA
pg_extended-0.0.1b1.dist-info/WHEEL
pg_extended-0.0.1b1.dist-info/top_level.txt
pg_extended-0.0.1b1.dist-info/RECORD
