Metadata-Version: 2.4
Name: pg-extended
Version: 0.0.1b1
Summary: A lightweight 2d game engine built on top of pygame.
Author-email: Saurabh Jadhav <pgextended.2025@gmail.com>
License: MIT
Project-URL: Homepage, https://github.com/Saurabh262004/pg-extended
Requires-Python: >=3.9
License-File: LICENSE
Requires-Dist: pygame-ce
Requires-Dist: pyperclip
Requires-Dist: easygui
Dynamic: license-file
